ncw/__init__.py
ncw/__main__.py
ncw/cache.py
ncw/commons.py
ncw/components.py
ncw/inner_structures.py
ncw/locks.py
ncw/nested_collections.py
ncw/py.typed
ncw/wrappers.py
ncw-0.5.3.dist-info/WHEEL
ncw-0.5.3.dist-info/entry_points.txt
ncw-0.5.3.dist-info/METADATA
ncw-0.5.3.dist-info/RECORD
