Metadata-Version: 2.3
Name: ncw
Version: 0.5.3
Summary: Nested collections wrapper
Keywords: nested-collections
Author: Rainer Schwarzbach
Author-email: Rainer Schwarzbach <rainer@blackstream.de>
License: MIT No Attribution
Classifier: Development Status :: 4 - Beta
Classifier: License :: OSI Approved :: MIT License
Classifier: Operating System :: OS Independent
Classifier: Programming Language :: Python :: 3
Classifier: Programming Language :: Python :: 3.10
Classifier: Programming Language :: Python :: 3.11
Classifier: Programming Language :: Python :: 3.12
Classifier: Programming Language :: Python :: 3.13
Classifier: Programming Language :: Python :: 3.14
Classifier: Programming Language :: Python :: 3 :: Only
Classifier: Topic :: Software Development :: Libraries :: Python Modules
Classifier: Intended Audience :: Developers
Requires-Dist: tomli>=1.1.0 ; python_full_version < '3.11'
Requires-Python: >=3.10
Project-URL: Bug Tracker, https://gitlab.com/blackstream-x/ncw/-/issues
Project-URL: CI, https://gitlab.com/blackstream-x/ncw/-/pipelines
Project-URL: Documentation, https://blackstream-x.gitlab.io/ncw/
Project-URL: Homepage, https://gitlab.com/blackstream-x/ncw
Project-URL: Repository, https://gitlab.com/blackstream-x/ncw.git
